MANIFEST.in
README.rst
entry_points.ini
setup.cfg
setup.py
src/Anthrax.egg-info/PKG-INFO
src/Anthrax.egg-info/SOURCES.txt
src/Anthrax.egg-info/dependency_links.txt
src/Anthrax.egg-info/entry_points.txt
src/Anthrax.egg-info/namespace_packages.txt
src/Anthrax.egg-info/requires.txt
src/Anthrax.egg-info/top_level.txt
src/anthrax/__init__.py
src/anthrax/exc.py
src/anthrax/frontend.py
src/anthrax/reflector.py
src/anthrax/util.py
src/anthrax/container/__init__.py
src/anthrax/container/base.py
src/anthrax/container/form.py
src/anthrax/field/__init__.py
src/anthrax/field/action.py
src/anthrax/field/base.py
src/anthrax/field/choice.py
src/anthrax/field/complex.py
src/anthrax/field/date_time.py
src/anthrax/field/file.py
src/anthrax/field/numeric.py
src/anthrax/field/ordered.py
src/anthrax/field/text.py
src/anthrax/validator/__init__.py
src/anthrax/validator/compare.py
src/anthrax/widget/__init__.py
src/anthrax/widget/action.py
src/anthrax/widget/base.py
src/anthrax/widget/date_time.py
src/anthrax/widget/file.py
src/anthrax/widget/numeric.py
src/anthrax/widget/select.py
src/anthrax/widget/simple.py