Metadata-Version: 1.1
Name: Anthrax
Version: 0.0.8
Summary: Form generation lib to end all form generation lib
Home-page: http://github.com/zefciu/Anthrax
Author: Szymon Pyżalski
Author-email: zefciu <szymon@pythonista.net>
License: UNKNOWN
Keywords: form web
Platform: UNKNOWN
Classifier: Development Status :: 1 - Planning
Classifier: Intended Audience :: Developers
Classifier: License :: OSI Approved :: BSD License
Classifier: Programming Language :: Python :: 3
Classifier: Programming Language :: Python :: 3.2
Classifier: Topic :: Internet :: WWW/HTTP :: Dynamic Content
